auto_coder_chat_lite/__init__.py
auto_coder_chat_lite/agent.py
auto_coder_chat_lite/chat.py
auto_coder_chat_lite/command_completer.py
auto_coder_chat_lite/common/__init__.py
auto_coder_chat_lite/common/code_auto_merge_editblock.py
auto_coder_chat_lite/common/command_completer.py
auto_coder_chat_lite/common/config_manager.py
auto_coder_chat_lite/common/git_diff_extractor.py
auto_coder_chat_lite/common/git_utils.py
auto_coder_chat_lite/common/text.py
auto_coder_chat_lite/common/utils.py
auto_coder_chat_lite/configuration_handler.hy
auto_coder_chat_lite/constants.hy
auto_coder_chat_lite/lang.py
auto_coder_chat_lite/lib/__init__.py
auto_coder_chat_lite/lib/agent.hy
auto_coder_chat_lite/lib/logger.hy
auto_coder_chat_lite/lib/merge.hy
auto_coder_chat_lite/lib/prompt.hy
auto_coder_chat_lite/project.py
auto_coder_chat_lite/prompt.py
auto_coder_chat_lite/template/code.txt
auto_coder_chat_lite/template/code_git_diff.txt
auto_coder_chat_lite/template/code_hylang.txt
auto_coder_chat_lite/template/code_search_replace.txt
auto_coder_chat_lite/template/commit_message.txt
auto_coder_chat_lite/template/hylang_grammer.txt
auto_coder_chat_lite/utils/__init__.py
auto_coder_chat_lite/utils/conversation_store.py
auto_coder_chat_lite/utils/log_capture.py
auto_coder_chat_lite/utils/multi_turn.py
auto_coder_chat_lite/utils/queue_communicate.py
auto_coder_chat_lite/utils/request_event_queue.py
auto_coder_chat_lite/utils/request_queue.py
auto_coder_chat_lite-0.1.13.dist-info/LICENSE
auto_coder_chat_lite-0.1.13.dist-info/METADATA
auto_coder_chat_lite-0.1.13.dist-info/WHEEL
auto_coder_chat_lite-0.1.13.dist-info/entry_points.txt
auto_coder_chat_lite-0.1.13.dist-info/RECORD
