Metadata-Version: 2.1
Name: auto-coder-chat-lite
Version: 0.1.13
Summary: a simple code chat tool inspired by auto coder
Author: cowboy
Author-email: 251027705@qq.com
Requires-Python: >=3.8.0,<3.14
Classifier: License :: OSI Approved :: MIT License
Classifier: Operating System :: OS Independent
Classifier: Programming Language :: Python :: 3
Classifier: Programming Language :: Python :: 3.8
Classifier: Programming Language :: Python :: 3.9
Classifier: Programming Language :: Python :: 3.10
Classifier: Programming Language :: Python :: 3.11
Classifier: Programming Language :: Python :: 3.12
Classifier: Programming Language :: Python :: 3.13
Requires-Dist: GitPython (==3.1.43)
Requires-Dist: Jinja2 (==3.1.4)
Requires-Dist: Pygments (==2.18.0)
Requires-Dist: colorama (==0.4.6)
Requires-Dist: hy (>=1.0.0,<2.0.0)
Requires-Dist: hyrule (>=0.7.0,<0.8.0)
Requires-Dist: loguru (>=0.7.2,<0.8.0)
Requires-Dist: openai (==1.44.1)
Requires-Dist: pathspec (==0.12.1)
Requires-Dist: prompt_toolkit (==3.0.47)
Requires-Dist: pydantic (==2.8.2)
Requires-Dist: pylint (==3.2.7)
Requires-Dist: pyperclip (==1.9.0)
Requires-Dist: rich (==13.7.1)
Requires-Dist: toolz (>=0.12.1,<0.13.0)
